doc_vault/__init__.py
doc_vault/config.py
doc_vault/core.py
doc_vault/exceptions.py
doc_vault/database/__init__.py
doc_vault/database/init_db.py
doc_vault/database/postgres_manager.py
doc_vault/database/repositories/__init__.py
doc_vault/database/repositories/acl.py
doc_vault/database/repositories/agent.py
doc_vault/database/repositories/base.py
doc_vault/database/repositories/document.py
doc_vault/database/repositories/organization.py
doc_vault/database/repositories/version.py
doc_vault/database/schemas/__init__.py
doc_vault/database/schemas/acl.py
doc_vault/database/schemas/agent.py
doc_vault/database/schemas/document.py
doc_vault/database/schemas/organization.py
doc_vault/database/schemas/version.py
doc_vault/database/sql/schema.sql
doc_vault/services/__init__.py
doc_vault/services/access_service.py
doc_vault/services/document_service.py
doc_vault/services/version_service.py
doc_vault/storage/__init__.py
doc_vault/storage/base.py
doc_vault/storage/s3_client.py
docvault_sdk-1.0.0.dist-info/METADATA
docvault_sdk-1.0.0.dist-info/WHEEL
docvault_sdk-1.0.0.dist-info/licenses/LICENSE
docvault_sdk-1.0.0.dist-info/RECORD
