Metadata-Version: 2.4
Name: docvault-sdk
Version: 1.0.0
Summary: Scalable Python SDK for document management and collaboration across organizations and AI agents
Project-URL: Homepage, https://github.com/docvault/doc-vault
Project-URL: Documentation, https://docvault.readthedocs.io/
Project-URL: Repository, https://github.com/docvault/doc-vault
Project-URL: Issues, https://github.com/docvault/doc-vault/issues
Project-URL: Changelog, https://github.com/docvault/doc-vault/blob/main/CHANGELOG.md
Author-email: DocVault Team <team@docvault.dev>
Maintainer-email: DocVault Team <team@docvault.dev>
License: MIT License
License-File: LICENSE
Keywords: ai,collaboration,document,management,organization,sdk
Classifier: Development Status :: 5 - Production/Stable
Classifier: Intended Audience :: Developers
Classifier: License :: OSI Approved :: MIT License
Classifier: Operating System :: OS Independent
Classifier: Programming Language :: Python :: 3
Classifier: Programming Language :: Python :: 3.10
Classifier: Programming Language :: Python :: 3.11
Classifier: Programming Language :: Python :: 3.12
Classifier: Topic :: Database
Classifier: Topic :: Internet :: WWW/HTTP
Classifier: Topic :: Software Development :: Libraries :: Python Modules
Classifier: Typing :: Typed
Requires-Python: >=3.10
Requires-Dist: minio
Requires-Dist: psqlpy
Requires-Dist: pydantic-settings<3.0,>=2.0
Requires-Dist: pydantic<3.0,>=2.0
Provides-Extra: all
Requires-Dist: doc-vault[dev,docs,lint,test]; extra == 'all'
Provides-Extra: dev
Requires-Dist: black<24.0,>=23.0; extra == 'dev'
Requires-Dist: mypy<2.0,>=1.0; extra == 'dev'
Requires-Dist: pre-commit; extra == 'dev'
Requires-Dist: pytest-asyncio<1.0,>=0.21; extra == 'dev'
Requires-Dist: pytest-cov<5.0,>=4.0; extra == 'dev'
Requires-Dist: pytest<8.0,>=7.0; extra == 'dev'
Requires-Dist: python-dotenv>=1.0.0; extra == 'dev'
Requires-Dist: ruff<1.0,>=0.1; extra == 'dev'
Provides-Extra: docs
Requires-Dist: myst-parser; extra == 'docs'
Requires-Dist: sphinx-rtd-theme; extra == 'docs'
Requires-Dist: sphinx>=5.0; extra == 'docs'
Provides-Extra: lint
Requires-Dist: black<24.0,>=23.0; extra == 'lint'
Requires-Dist: mypy<2.0,>=1.0; extra == 'lint'
Requires-Dist: ruff<1.0,>=0.1; extra == 'lint'
Provides-Extra: test
Requires-Dist: pytest-asyncio<1.0,>=0.21; extra == 'test'
Requires-Dist: pytest-cov<5.0,>=4.0; extra == 'test'
Requires-Dist: pytest<8.0,>=7.0; extra == 'test'
